vonage_verify/__init__.py
vonage_verify/_version.py
vonage_verify/errors.py
vonage_verify/language_codes.py
vonage_verify/requests.py
vonage_verify/responses.py
vonage_verify/verify.py
vonage_verify-1.1.3.dist-info/METADATA
vonage_verify-1.1.3.dist-info/WHEEL
vonage_verify-1.1.3.dist-info/top_level.txt
vonage_verify-1.1.3.dist-info/RECORD
