Metadata-Version: 2.1
Name: vonage-verify
Version: 1.1.3
Summary: Vonage verify package
Author-email: Vonage <devrel@vonage.com>
Project-URL: homepage, https://github.com/Vonage/vonage-python-sdk
Classifier: Programming Language :: Python
Classifier: Programming Language :: Python :: 3
Classifier: Programming Language :: Python :: 3.9
Classifier: Programming Language :: Python :: 3.10
Classifier: Programming Language :: Python :: 3.11
Classifier: Programming Language :: Python :: 3.12
Classifier: Programming Language :: Python :: 3.13
Classifier: License :: OSI Approved :: Apache Software License
Requires-Python: >=3.9
Requires-Dist: vonage-http-client>=1.4.2
Requires-Dist: vonage-utils>=1.1.4
Requires-Dist: pydantic>=2.9.2
